{
  "room_metadata": {
    "name": "โถงทางเดินชั้น 2 (Hallway - 2nd Floor)",
    "location": "ชั้นสอง (Second Floor)",
    "atmosphere": "ลมพัดกรรโชกแรงผ่านผ้าม่านที่เปิดอยู่ โคมไฟระย้าเหวี่ยงไปมาส่งเสียงเอี๊ยดอ๊าด และทางลงบันไดมืดมิดเจือไปด้วยฝุ่น",
    "state": "Dangerous/Unstable"
  },
  "room_contents": {
    "furniture": [
      {
        "name": "พรมเช็ดเท้า (Rug)",
        "description": "พรมวางอยู่ตรงปากทางลงบันไดในสภาพยับยู่ยี่ เสี่ยงต่อการสะดุดล้มหากผู้เล่นไม่ก้มลงไปจัดระเบียบให้เรียบร้อย"
      },
      {
        "name": "โคมไฟระย้า (Chandelier)",
        "description": "โคมไฟขนาดใหญ่บนเพดานที่เหวี่ยงไปมาอย่างรุนแรงตามแรงลม หากอยู่ใต้โคมไฟที่กำลังแกว่งหรือปล่อยเวลาผ่านไปนานเกินไป โคมไฟจะหลุดร่วงลงมาทับ"
      }
    ],
    "objects": [
      {
        "name": "ผ้าม่านหน้าต่างบานใหญ่ (Large Window Curtain)",
        "description": "ผ้าม่านที่กำลังปลิวไหวจากกระแสลมที่ลอดผ่านหน้าต่างบานใหญ่ ผู้เล่นต้องรีบพุ่งเข้าไปปิดให้สนิทเพื่อหยุดพายุลมที่พัดเข้ามา และทำให้โคมไฟระย้าหยุดแกว่ง"
      },
      {
        "name": "สวิตช์ไฟขั้นบันได (Stair Light Switch)",
        "description": "สวิตช์ควบคุมแสงสว่างบริเวณโถงบันได ซึ่งจำเป็นต้องเปิดเพื่อให้แสงสว่างสาดส่องลงไป ป้องกันการก้าวพลาดตกบันไดในความมืด"
      }
    ],
    "exits": [
      {
        "name": "บันไดลงไปชั้น 1 (Stairs down to 1st Floor)",
        "status": "เปิดอยู่ (แต่จะลงได้อย่างปลอดภัยก็ต่อเมื่อ ปิดม่าน จัดพรม และเปิดสวิตช์ไฟเสร็จสิ้นแล้วเท่านั้น)"
      },
      {
        "name": "ประตูกลับห้องนอน (Door back to bedroom)",
        "status": "เปิดอยู่สามารถเดินย้อนกลับไปได้เสมอ"
      }
    ]
  },
  "room_objects_bounding_boxes": [
    {
      "name": "ผ้าม่านหน้าต่างบานใหญ่ (Large Window Curtain)",
      "bounding_box": {
        "left": 33.5,
        "top": 29.5,
        "width": 34.5,
        "height": 31.5
      }
    },
    {
      "name": "โคมไฟระย้า (Chandelier)",
      "bounding_box": {
        "left": 55.0,
        "top": 12.5,
        "width": 20.5,
        "height": 28.5
      }
    },
    {
      "name": "พรมเช็ดเท้า (Rug)",
      "bounding_box": {
        "left": 20.5,
        "top": 84.5,
        "width": 19.5,
        "height": 13.5
      }
    },
    {
      "name": "สวิตช์ไฟขั้นบันได (Stair Light Switch)",
      "bounding_box": {
        "left": 16.8,
        "top": 52.8,
        "width": 1.8,
        "height": 6.2
      }
    },
    {
      "name": "บันไดลงไปชั้น 1 (Stairs down to 1st Floor)",
      "bounding_box": {
        "left": 41.5,
        "top": 61.5,
        "width": 45.0,
        "height": 38.5
      }
    },
    {
      "name": "ประตูกลับห้องนอน (Door back to bedroom)",
      "bounding_box": {
        "left": 5.2,
        "top": 25.5,
        "width": 10.5,
        "height": 72.5
      }
    }
  ]
}
